__init__.py
src/example_package_team8/typer_main.py
example_package_team8-0.0.1.dist-info/METADATA
example_package_team8-0.0.1.dist-info/WHEEL
example_package_team8-0.0.1.dist-info/licenses/LICENSE
example_package_team8-0.0.1.dist-info/RECORD
